deel/puncc/__init__.py
deel/puncc/anomaly_detection.py
deel/puncc/classification.py
deel/puncc/metrics.py
deel/puncc/object_detection.py
deel/puncc/plotting.py
deel/puncc/regression.py
deel/puncc/api/__init__.py
deel/puncc/api/calibration.py
deel/puncc/api/conformalization.py
deel/puncc/api/corrections.py
deel/puncc/api/experimental.py
deel/puncc/api/nonconformity_scores.py
deel/puncc/api/prediction.py
deel/puncc/api/prediction_sets.py
deel/puncc/api/splitting.py
deel/puncc/api/utils.py
puncc-0.8.0.dist-info/METADATA
puncc-0.8.0.dist-info/WHEEL
puncc-0.8.0.dist-info/top_level.txt
puncc-0.8.0.dist-info/RECORD
