Metadata-Version: 2.1
Name: puncc
Version: 0.8.0
Summary: Predictive UNcertainty Calibration and Conformalization Library
Home-page: https://github.com/deel-ai/puncc
Author: Mouhcine Mendil, Luca Mossina, Joseba Dalmau
Author-email: mouhcine.mendil@irt-saintexupery.com, luca.mossina@irt-saintexupery.com, joseba.dalmau@irt-saintexupery.com
License: UNKNOWN
Platform: UNKNOWN
Classifier: License :: OSI Approved :: MIT License
Classifier: Programming Language :: Python
Classifier: Programming Language :: Python :: 3
Classifier: Operating System :: OS Independent
Requires-Python: >=3.8
Requires-Dist: joblib
Requires-Dist: matplotlib
Requires-Dist: numpy
Requires-Dist: pandas
Requires-Dist: scikit-learn
Requires-Dist: tqdm
Provides-Extra: dev
Requires-Dist: flake8; extra == "dev"
Requires-Dist: pylint; extra == "dev"
Requires-Dist: pytest; extra == "dev"
Requires-Dist: pytest-cov; extra == "dev"
Requires-Dist: black; extra == "dev"
Requires-Dist: pre-commit; extra == "dev"
Requires-Dist: sphinx; extra == "dev"
Requires-Dist: sphinx-rtd-theme; extra == "dev"
Requires-Dist: sphinx-autodoc-typehints; extra == "dev"
Requires-Dist: tensorflow; extra == "dev"
Requires-Dist: tensorflow-addons; extra == "dev"
Requires-Dist: tox; extra == "dev"
Provides-Extra: interactive
Requires-Dist: ipykernel; extra == "interactive"
